tronhex/__init__.py
tronhex/main.py
tronhex-0.0.1.dist-info/licenses/LICENSE.txt
tronhex-0.0.1.dist-info/METADATA
tronhex-0.0.1.dist-info/WHEEL
tronhex-0.0.1.dist-info/top_level.txt
tronhex-0.0.1.dist-info/RECORD
