Metadata-Version: 2.4
Name: tronhex
Version: 0.0.1
Summary: tronhex library for Python
Author: riktron
Author-email: kentkouh+updri@gmail.com
License: MIT
Project-URL: Source Repository, https://github.com
License-File: LICENSE.txt
Requires-Dist: requests
Dynamic: author
Dynamic: author-email
Dynamic: description
Dynamic: description-content-type
Dynamic: license
Dynamic: license-file
Dynamic: project-url
Dynamic: requires-dist
Dynamic: summary
